code/cpu/interconnect/gp_fifo.v
/*

File: gp_fifo.v
Descripton: Simple FIFO module

General purpose FIFO to handle the read and write buffer.
The whole FIFO runs on the same clock domain (ie. not the async version )

32 slots of 34 bits

*/

module gp_fifo(
    input clk,
    input reset,
    input write_en,
    input read_en,
    input [33:0] data_in,
    output wire [33:0] data_out,
    output wire error,
    output wire full,
    output wire empty,
    output wire [4:0] ocup
);

    // this is one less than MSB (32bit -> 5 )
    `define MSB_SLOT 4

    reg [33:0] fifo_ff [31:0]; 
    reg [`MSB_SLOT:0] write_ptr_ff,read_ptr_ff;
    wire [`MSB_SLOT:0] next_write_ptr, next_read_ptr,fifo_ocup;

    // check hear for combinational logic
    // assign next_read_ptr = read_ptr_ff;
    // assign next_write_ptr = write_ptr_ff;

    assign empty = (write_ptr_ff == read_ptr_ff);
    assign full = (write_ptr_ff[`MSB_SLOT-1:0] == read_ptr_ff[`MSB_SLOT-1:0] )  && (write_ptr_ff[`MSB_SLOT]!= read_ptr_ff[`MSB_SLOT]);
            
    assign data_out = empty ? 1'b0 : fifo_ff[read_ptr_ff[`MSB_SLOT-1:0]];
    
    assign next_write_ptr =  (write_en && ~full) ? write_ptr_ff + 1'b1: write_ptr_ff;

    assign next_read_ptr =   (read_en && ~empty) ? read_ptr_ff + 1'b1 : read_ptr_ff;

    assign error = (write_en && full) || (read_en && empty);
    assign fifo_ocup = write_ptr_ff - read_ptr_ff;
    assign ocup = fifo_ocup;

    // always@*begin
    //     next_read_ptr = read_ptr_ff;
    //     next_write_ptr = write_ptr_ff;

    //     empty = (write_ptr_ff == read_ptr_ff);
    //     full = (write_ptr_ff[`MSB_SLOT-1:0] == read_ptr_ff[`MSB_SLOT-1:0] )  && (write_ptr_ff[`MSB_SLOT]!= read_ptr_ff[`MSB_SLOT]);
                
    //     data_out = empty ? 0 : fifo_ff[read_ptr_ff[`MSB_SLOT-1:0]];
        
    //     if (write_en && ~full)
    //         next_write_ptr = write_ptr_ff + 1'b1;

    //     if (read_en && ~empty)
    //         next_read_ptr = read_ptr_ff + 1'b1;

    //     error = (write_en && full) || (read_en && empty);
    //     fifo_ocup = write_ptr_ff - read_ptr_ff;
    //     ocup = fifo_ocup;
    // end

    integer i;
    always@(posedge clk or posedge reset)begin
        if(reset) begin
            write_ptr_ff <= 1'b0;
            read_ptr_ff <= 1'b0;
            for (i = 0; i < 32; i = i + 1)
            begin
                fifo_ff[i] <= 0;       // Write zero to all registers
            end
        end
        else begin
            write_ptr_ff <= next_write_ptr;
            read_ptr_ff <= next_read_ptr;
            if (write_en && ~full)
                fifo_ff[write_ptr_ff[`MSB_SLOT-1:0]] <= data_in;
        end
    end
endmodule

code/cpu/interconnect/interconnect.v
/*
File: interconnect.v
Description: Temporary module to connect two Cores 

*/

`include "../../interconnect/gp_fifo.v"

module interconnect(
    input wire clk,
    input wire reset,
    input wire [1:0] a_n_addr_in,
    input wire [31:0] a_data_in, 
    output wire [1:0] a_n_addr_out,
    output wire [31:0] a_data_out,
    input wire a_read_en,
    input wire a_write_en,
    input wire [1:0] b_n_addr_in,
    input wire [31:0] b_data_in, 
    output wire [1:0] b_n_addr_out,
    output wire [31:0] b_data_out,
    input wire b_read_en,
    input wire b_write_en
);

    /*
    module gp_fifo(
        input clk,
        input reset,
        input write_en,
        input read_en,
        input [63:0] data_in,
        output reg [63:0] data_out,
        output reg error,
        output reg full,
        output reg empty,
        output reg [4:0] ocup
    );


    */

    wire [4:0] atob_ocup,btoa_ocup;
    wire atob_full, atob_empty, atob_err, btoa_full, btoa_empty, btoa_err;
    
    wire [33:0] atob_data_in,atob_data_out,btoa_data_in,btoa_data_out;

    //  ==== IF WE DONT CARE ABOUT SIGNALS AND JUST WANT 
    // TO SEND DATA USE THE ASSIGNS HERE =============
    // assign b_n_addr_out = a_n_addr_in;
    // assign b_data_out = a_data_in;

    // assign a_n_addr_out = b_n_addr_in;
    // assign a_data_out = b_data_in;
    
    assign atob_data_in[33:32] = a_n_addr_in; 
    assign atob_data_in[31:0] = a_data_in; 
    assign btoa_data_in[33:32] = b_n_addr_in; 
    assign btoa_data_in[31:0] = b_data_in; 
    

    assign a_n_addr_out = btoa_data_out[33:32];
    assign a_data_out = btoa_data_out[31:0]; 
    assign b_n_addr_out = atob_data_out[33:32];
    assign b_data_out = atob_data_out[31:0]; 

    gp_fifo atob(
        clk,
        reset,
        a_write_en,
        b_read_en,
        atob_data_in,
        atob_data_out,
        atob_err,
        atob_full,
        atob_empty,
        atob_ocup
    );

    gp_fifo btoa(
        clk,
        reset,
        b_write_en,
        a_read_en,
        btoa_data_in,
        btoa_data_out,
        btoa_err,
        btoa_full,
        btoa_empty,
        btoa_ocup
    );
endmodule

code/cpu/testbench/interconnect/interconnect_tb.v
`timescale 1ns / 1ps
`include "../../interconnect/interconnect.v"

module interconnect_tb();
    reg clk;
    reg reset;

    reg [1:0] a_n_addr_in;
    reg [31:0] a_data_in;
    wire [1:0] a_n_addr_out;
    wire [31:0] a_data_out;
    reg a_read_en;
    reg a_write_en;

    reg [1:0] b_n_addr_in;
    reg [31:0] b_data_in; 
    wire [1:0] b_n_addr_out;
    wire [31:0] b_data_out;
    reg b_read_en;
    reg b_write_en;

    interconnect my_in(
        clk,
        reset,
        a_n_addr_in,
        a_data_in, 
        a_n_addr_out,
        a_data_out,
        a_read_en,
        a_write_en,
        b_n_addr_in,
        b_data_in, 
        b_n_addr_out,
        b_data_out,
        b_read_en,
        b_write_en
    );

    /*
    
    For simulation assuming neuron division as follows
    - core 1 => 2'b00
    - core 2 => 2'b01, 2'b10 
    
    */

    // VCD dump file
    initial begin
        $dumpfile("in_tb.vcd");
        $dumpvars(0, interconnect_tb);

        // Initalize signals
        
        clk = 1'b0;
        reset = 1'b1;
        a_n_addr_in = 2'b00;
        a_data_in = 32'h0;
        a_read_en = 1'b0; 
        a_write_en = 1'b0;

        b_n_addr_in = 2'b00;
        b_data_in  = 32'h0;
        b_read_en = 1'b0;
        b_write_en = 1'b0;

        #10;
        
        reset = 1'b0;
        a_n_addr_in = 2'b01;
        a_data_in = 32'hA5A5A5A5;
        a_read_en = 1'b0; 
        a_write_en = 1'b1;

        b_n_addr_in = 2'b00;
        b_data_in  = 32'hABABABAB;
        b_read_en = 1'b0;
        b_write_en = 1'b1;


        #10;
        reset = 1'b0;
        a_n_addr_in = 2'b10;
        a_data_in = 32'hAAAAAAAA;
        a_read_en = 1'b0; 
        a_write_en = 1'b1;

        b_n_addr_in = 2'b00;
        b_data_in  = 32'hBBBBBBAB;
        b_read_en = 1'b0;
        b_write_en = 1'b1;

        #10;
        reset = 1'b0;
        a_n_addr_in = 2'b01;
        a_data_in = 32'hAAAAAAAA;
        a_read_en = 1'b1; 
        a_write_en = 1'b0;

        b_n_addr_in = 2'b00;
        b_data_in  = 32'hBBBBBBAB;
        b_read_en = 1'b1;
        b_write_en = 1'b0;


        #10;
        reset = 1'b0;
        a_n_addr_in = 2'b01;
        a_data_in = 32'hAAAAAAAA;
        a_read_en = 1'b1; 
        a_write_en = 1'b0;

        b_n_addr_in = 2'b00;
        b_data_in  = 32'hBBBBBBAB;
        b_read_en = 1'b1;
        b_write_en = 1'b0;

        #10;
        // Perform additional read and write operations as needed
        // End simulation
        $finish;
    end

    // Clock generation
    always begin
        #5 clk = ~clk;
    end

endmodule

code/cpu/testbench/interconnect/in_tb.vcd
$date
	Fri Nov 10 11:00:17 2023
$end
$version
	Icarus Verilog
$end
$timescale
	1ps
$end
$scope module interconnect_tb $end
$var wire 2 ! b_n_addr_out [1:0] $end
$var wire 32 " b_data_out [31:0] $end
$var wire 2 # a_n_addr_out [1:0] $end
$var wire 32 $ a_data_out [31:0] $end
$var reg 32 % a_data_in [31:0] $end
$var reg 2 & a_n_addr_in [1:0] $end
$var reg 1 ' a_read_en $end
$var reg 1 ( a_write_en $end
$var reg 32 ) b_data_in [31:0] $end
$var reg 2 * b_n_addr_in [1:0] $end
$var reg 1 + b_read_en $end
$var reg 1 , b_write_en $end
$var reg 1 - clk $end
$var reg 1 . reset $end
$scope module my_in $end
$var wire 32 / a_data_in [31:0] $end
$var wire 2 0 a_n_addr_in [1:0] $end
$var wire 1 ' a_read_en $end
$var wire 1 ( a_write_en $end
$var wire 32 1 b_data_in [31:0] $end
$var wire 2 2 b_n_addr_in [1:0] $end
$var wire 1 + b_read_en $end
$var wire 1 , b_write_en $end
$var wire 1 - clk $end
$var wire 1 . reset $end
$var wire 5 3 btoa_ocup [4:0] $end
$var wire 1 4 btoa_full $end
$var wire 1 5 btoa_err $end
$var wire 1 6 btoa_empty $end
$var wire 34 7 btoa_data_out [33:0] $end
$var wire 34 8 btoa_data_in [33:0] $end
$var wire 2 9 b_n_addr_out [1:0] $end
$var wire 32 : b_data_out [31:0] $end
$var wire 5 ; atob_ocup [4:0] $end
$var wire 1 < atob_full $end
$var wire 1 = atob_err $end
$var wire 1 > atob_empty $end
$var wire 34 ? atob_data_out [33:0] $end
$var wire 34 @ atob_data_in [33:0] $end
$var wire 2 A a_n_addr_out [1:0] $end
$var wire 32 B a_data_out [31:0] $end
$scope module atob $end
$var wire 1 - clk $end
$var wire 34 C data_in [33:0] $end
$var wire 1 = error $end
$var wire 1 < full $end
$var wire 5 D ocup [4:0] $end
$var wire 1 + read_en $end
$var wire 1 . reset $end
$var wire 1 ( write_en $end
$var wire 5 E next_write_ptr [4:0] $end
$var wire 5 F next_read_ptr [4:0] $end
$var wire 5 G fifo_ocup [4:0] $end
$var wire 1 > empty $end
$var wire 34 H data_out [33:0] $end
$var reg 5 I read_ptr_ff [4:0] $end
$var reg 5 J write_ptr_ff [4:0] $end
$var integer 32 K i [31:0] $end
$upscope $end
$scope module btoa $end
$var wire 1 - clk $end
$var wire 34 L data_in [33:0] $end
$var wire 1 5 error $end
$var wire 1 4 full $end
$var wire 5 M ocup [4:0] $end
$var wire 1 ' read_en $end
$var wire 1 . reset $end
$var wire 1 , write_en $end
$var wire 5 N next_write_ptr [4:0] $end
$var wire 5 O next_read_ptr [4:0] $end
$var wire 5 P fifo_ocup [4:0] $end
$var wire 1 6 empty $end
$var wire 34 Q data_out [33:0] $end
$var reg 5 R read_ptr_ff [4:0] $end
$var reg 5 S write_ptr_ff [4:0] $end
$var integer 32 T i [31:0] $end
$upscope $end
$upscope $end
$upscope $end
$enddefinitions $end
#0
$dumpvars
b100000 T
b0 S
b0 R
b0 Q
b0 P
b0 O
b0 N
b0 M
b0 L
b100000 K
b0 J
b0 I
b0 H
b0 G
b0 F
b0 E
b0 D
b0 C
b0 B
b0 A
b0 @
b0 ?
1>
0=
0<
b0 ;
b0 :
b0 9
b0 8
b0 7
16
05
04
b0 3
b0 2
b0 1
b0 0
b0 /
1.
0-
0,
0+
b0 *
b0 )
0(
0'
b0 &
b0 %
b0 $
b0 #
b0 "
b0 !
$end
#5000
b100000 T
b100000 K
1-
#10000
b1 N
b1 E
0-
1,
b10101011101010111010101110101011 8
b10101011101010111010101110101011 L
b10101011101010111010101110101011 )
b10101011101010111010101110101011 1
1(
b10100101101001011010010110100101 %
b10100101101001011010010110100101 /
b110100101101001011010010110100101 @
b110100101101001011010010110100101 C
b1 &
b1 0
0.
#15000
b10100101101001011010010110100101 "
b10100101101001011010010110100101 :
b1 !
b1 9
b10101011101010111010101110101011 $
b10101011101010111010101110101011 B
b110100101101001011010010110100101 ?
b110100101101001011010010110100101 H
b10 E
b10101011101010111010101110101011 7
b10101011101010111010101110101011 Q
b10 N
0>
b1 ;
b1 D
b1 G
b1 J
06
b1 3
b1 M
b1 P
b1 S
1-
#20000
0-
b10111011101110111011101110101011 8
b10111011101110111011101110101011 L
b10111011101110111011101110101011 )
b10111011101110111011101110101011 1
b10101010101010101010101010101010 %
b10101010101010101010101010101010 /
b1010101010101010101010101010101010 @
b1010101010101010101010101010101010 C
b10 &
b10 0
#25000
b11 N
b11 E
b10 3
b10 M
b10 P
b10 S
b10 ;
b10 D
b10 G
b10 J
1-
#30000
b10 N
b1 F
b10 E
b1 O
0-
0,
1+
0(
1'
b110101010101010101010101010101010 @
b110101010101010101010101010101010 C
b1 &
b1 0
#35000
b10101010101010101010101010101010 "
b10101010101010101010101010101010 :
b10 !
b10 9
b10111011101110111011101110101011 $
b10111011101110111011101110101011 B
b1010101010101010101010101010101010 ?
b1010101010101010101010101010101010 H
b10111011101110111011101110101011 7
b10111011101110111011101110101011 Q
b10 F
b10 O
b1 ;
b1 D
b1 G
b1 I
b1 3
b1 M
b1 P
b1 R
1-
#40000
0-
#45000
b0 $
b0 B
15
b0 "
b0 :
b0 !
b0 9
1=
b0 7
b0 Q
b10 O
b0 ?
b0 H
b10 F
16
b0 3
b0 M
b0 P
b10 R
1>
b0 ;
b0 D
b0 G
b10 I
1-
